ao3_poster/__init__.py
ao3_poster/__version__.py
ao3_poster/ao3.py
ao3_poster/cli.py
ao3_poster/exceptions.py
ao3_poster-0.0.7.dist-info/LICENSE
ao3_poster-0.0.7.dist-info/METADATA
ao3_poster-0.0.7.dist-info/WHEEL
ao3_poster-0.0.7.dist-info/entry_points.txt
ao3_poster-0.0.7.dist-info/top_level.txt
ao3_poster-0.0.7.dist-info/RECORD
